Metadata-Version: 1.0
Name: S3ConfigLoader
Version: 0.1.5
Summary: This package implements a simple config property loader 
Home-page: UNKNOWN
Author: Rahul Subramaniam
Author-email: rahulsub@gmail.com    
License: PSF
Keywords: property configuration loader
Platform: UNKNOWN
